{
  "note": "店舗追加キュー。GitHub Actions（.github/workflows/daily-stores.yml）が毎日キュー先頭から正確に dripPerDay 件を data/spots.js へ反映し、使った分を消し込みます。lastRunDate が当日(JST)なら二重実行を防ぐため何もしません。有効候補が4件未満なら部分追加せず失敗します。queue へは公式一次情報で営業中を確認した店舗だけを追記し、sourceUrl と verifiedAt を必ず保存してください。id・店名の重複は検証で拒否します。",
  "dripPerDay": 4,
  "dailyMix": [],
  "lastRunDate": "2026-07-13",
  "queue": [
    {
      "id": "gashapon-bandai-plant-izumo",
      "brand": "ガシャポンバンダイオフィシャルショップ",
      "name": "ガシャポンバンダイオフィシャルショップPLANT出雲店",
      "region": "chugoku",
      "pref": "島根県",
      "area": "島根県・出雲",
      "address": "島根県出雲市塩冶町1408-2",
      "lat": 35.35925428783788,
      "lon": 132.74980169798624,
      "sourceUrl": "https://gashapon.jp/shop/shop.php?shop_code=S90001433",
      "verifiedAt": "2026-07-13"
    },
    {
      "id": "gashadepa-fujigran-iwakuni",
      "brand": "ガシャポンのデパート",
      "name": "ガシャポンのデパートフジグラン岩国店",
      "region": "chugoku",
      "pref": "山口県",
      "area": "山口県・岩国",
      "address": "山口県岩国市麻里布町2-9-8 フジグラン岩国店 5F",
      "lat": 34.168722,
      "lon": 132.223352,
      "sourceUrl": "https://gashapon.jp/shop/shop.php?shop_code=S90000480",
      "verifiedAt": "2026-07-13"
    },
    {
      "id": "gashapon-bandai-libro-moriya",
      "brand": "ガシャポンバンダイオフィシャルショップ",
      "name": "ガシャポンバンダイオフィシャルショップ リブロイオンタウン守谷店",
      "region": "kanto",
      "pref": "茨城県",
      "area": "茨城県・守谷",
      "address": "茨城県守谷市百合ケ丘3丁目249-1 イオンタウン守谷本館 2F",
      "lat": 35.9448157,
      "lon": 139.990594,
      "sourceUrl": "https://gashapon.jp/shop/shop.php?shop_code=S90000766",
      "verifiedAt": "2026-07-13"
    },
    {
      "id": "gashapon-bandai-aeoncinema-okayama",
      "brand": "ガシャポンバンダイオフィシャルショップ",
      "name": "ガシャポンバンダイオフィシャルショップイオンシネマ岡山店",
      "region": "chugoku",
      "pref": "岡山県",
      "area": "岡山県・岡山",
      "address": "岡山県岡山市北区下石井1-2-1 イオンモール岡山5F",
      "lat": 34.6620824,
      "lon": 133.9177261,
      "sourceUrl": "https://gashapon.jp/shop/shop.php?shop_code=S90000805",
      "verifiedAt": "2026-07-13"
    },
    {
      "id": "dreamcapsule-naha-opa",
      "brand": "ドリームカプセル",
      "name": "ドリームカプセル 那覇OPA",
      "region": "kyushu",
      "pref": "沖縄県",
      "area": "沖縄県・那覇",
      "address": "沖縄県那覇市泉崎1-20-1 カフーナ旭橋A街区",
      "lat": 26.2113208,
      "lon": 127.6764053,
      "sourceUrl": "https://gashapon.jp/shop/shop.php?shop_code=S90000932",
      "verifiedAt": "2026-07-13"
    },
    {
      "id": "capsulepark-kawatoku",
      "brand": "カプセルパーク",
      "name": "カプセルパーク川徳店",
      "region": "tohoku",
      "pref": "岩手県",
      "area": "岩手県・盛岡",
      "address": "岩手県盛岡市菜園1丁目10番1号 パルクアベニュー・カワトク 6F",
      "lat": 39.70088891960067,
      "lon": 141.14691601353593,
      "sourceUrl": "https://gashapon.jp/shop/shop.php?shop_code=S90001409",
      "verifiedAt": "2026-07-13"
    },
    {
      "id": "gashapon-bandai-tsutaya-miyazaki-takachiho-dori",
      "brand": "ガシャポンバンダイオフィシャルショップ",
      "name": "ガシャポンバンダイオフィシャルショップ蔦屋書店 宮崎高千穂通り店",
      "region": "kyushu",
      "pref": "宮崎県",
      "area": "宮崎県・宮崎",
      "address": "宮崎県宮崎市橘通東4丁目8-1 カリーノ宮崎 2F",
      "lat": 31.916618,
      "lon": 131.4250519,
      "sourceUrl": "https://gashapon.jp/shop/shop.php?shop_code=S90000964",
      "verifiedAt": "2026-07-13"
    },
    {
      "id": "cpla-kyoto-shijo-kawaramachi",
      "brand": "#C-pla（シープラ）",
      "name": "#C-pla京都四条河原町",
      "region": "kansai",
      "pref": "京都府",
      "area": "京都府・四条河原町",
      "address": "京都府京都市中京区河原町通三条下る山崎町2丁目258番地 AD-G四条河原町 1F",
      "lat": 35.006734252973935,
      "lon": 135.76899085837667,
      "sourceUrl": "https://gashapon.jp/shop/shop.php?shop_code=S90001209",
      "verifiedAt": "2026-07-13"
    },
    {
      "id": "ggmori-marugamemachi-green",
      "brand": "ガチャガチャの森",
      "name": "ガチャガチャの森丸亀町グリーン店",
      "region": "chugoku",
      "pref": "香川県",
      "area": "香川県・高松",
      "address": "香川県高松市丸亀町7番地16 丸亀町グリーン 西館2F",
      "lat": 34.3422143950302,
      "lon": 134.049279978923,
      "sourceUrl": "https://gashapon.jp/shop/shop.php?shop_code=S90001038",
      "verifiedAt": "2026-07-13"
    },
    {
      "id": "dreamcapsule-kochi-avenue",
      "brand": "ドリームカプセル",
      "name": "ドリームカプセル 高知アベニュー店",
      "region": "chugoku",
      "pref": "高知県",
      "area": "高知県・高知",
      "address": "高知県高知市帯屋町1丁目13-23 帯屋町商店街内 アベニュービル2F",
      "lat": 33.56017321307528,
      "lon": 133.53896577883248,
      "sourceUrl": "https://gashapon.jp/shop/shop.php?shop_code=S90001196",
      "verifiedAt": "2026-07-13"
    },
    {
      "id": "cpla-moraju-saga",
      "brand": "#C-pla（シープラ）",
      "name": "#C-plaモラージュ佐賀",
      "region": "kyushu",
      "pref": "佐賀県",
      "area": "佐賀県・佐賀",
      "address": "佐賀県佐賀市巨勢町牛島730",
      "lat": 33.25130185683441,
      "lon": 130.31926193768396,
      "sourceUrl": "https://gashapon.jp/shop/shop.php?shop_code=S90001437",
      "verifiedAt": "2026-07-13"
    },
    {
      "id": "gashapon-bandai-miraiya-tsu-shiroyama",
      "brand": "ガシャポンバンダイオフィシャルショップ",
      "name": "ガシャポンバンダイオフィシャルショップ未来屋書店津城山店",
      "region": "tokai",
      "pref": "三重県",
      "area": "三重県・津",
      "address": "三重県津市久居小野辺町1130-7 イオン津城山SC 2F",
      "lat": 34.67939320601478,
      "lon": 136.5013748296255,
      "sourceUrl": "https://gashapon.jp/shop/shop.php?shop_code=S90001223",
      "verifiedAt": "2026-07-13"
    },
    {
      "id": "gashapon-bandai-fumotto-minami-alps",
      "brand": "ガシャポンバンダイオフィシャルショップ",
      "name": "ガシャポンバンダイオフィシャルショップfumotto南アルプス店",
      "region": "kanto",
      "pref": "山梨県",
      "area": "山梨県・南アルプス",
      "address": "山梨県南アルプス市十日市場1571-1 fumotto南アルプス内",
      "lat": 35.61263412001422,
      "lon": 138.4819199557557,
      "sourceUrl": "https://gashapon.jp/shop/shop.php?shop_code=S90001667",
      "verifiedAt": "2026-07-13"
    },
    {
      "id": "cpla-ohme-otsu-terrace",
      "brand": "#C-pla（シープラ）",
      "name": "#C-plaOh!Me大津テラス",
      "region": "kansai",
      "pref": "滋賀県",
      "area": "滋賀県・大津",
      "address": "滋賀県大津市打出浜14-30 Oh!Me大津テラス 5F 503区画",
      "lat": 35.004307145337066,
      "lon": 135.8797953040894,
      "sourceUrl": "https://gashapon.jp/shop/shop.php?shop_code=S90001536",
      "verifiedAt": "2026-07-13"
    },
    {
      "id": "ggmori-centerrace-tenmonkan",
      "brand": "ガチャガチャの森",
      "name": "ガチャガチャの森センテラス天文館店",
      "region": "kyushu",
      "pref": "鹿児島県",
      "area": "鹿児島県・天文館",
      "address": "鹿児島県鹿児島市千日町1-1 センテラス天文館2F",
      "lat": 31.5902029210204,
      "lon": 130.554861738695,
      "sourceUrl": "https://gashapon.jp/shop/shop.php?shop_code=S90001047",
      "verifiedAt": "2026-07-13"
    },
    {
      "id": "gashapon-bandai-miraiya-niigata-aoyama",
      "brand": "ガシャポンバンダイオフィシャルショップ",
      "name": "ガシャポンバンダイオフィシャルショップ未来屋書店新潟青山店",
      "region": "tohoku",
      "pref": "新潟県",
      "area": "新潟県・青山",
      "address": "新潟県新潟市西区青山2丁目5-1 イオン新潟青山店2F",
      "lat": 37.8963783,
      "lon": 139.0049982,
      "sourceUrl": "https://gashapon.jp/shop/shop.php?shop_code=S90000958",
      "verifiedAt": "2026-07-13"
    },
    {
      "id": "dreamcapsule-ciinaciina-aomori",
      "brand": "ドリームカプセル",
      "name": "ドリームカプセル シーナシーナ青森店",
      "region": "tohoku",
      "pref": "青森県",
      "area": "青森県・青森",
      "address": "青森県青森市浜田1丁目14-1 CiiNA CiiNA青森 1F",
      "lat": 40.8009576,
      "lon": 140.7490938,
      "sourceUrl": "https://gashapon.jp/shop/shop.php?shop_code=S90000765",
      "verifiedAt": "2026-07-13"
    },
    {
      "id": "gashapon-bandai-lalaport-iwata",
      "brand": "ガシャポンバンダイオフィシャルショップ",
      "name": "ガシャポンバンダイオフィシャルショップららぽーと磐田店",
      "region": "tokai",
      "pref": "静岡県",
      "area": "静岡県・磐田",
      "address": "静岡県磐田市高見丘1200 ららぽーと磐田2F",
      "lat": 34.75028667290205,
      "lon": 137.84188906786738,
      "sourceUrl": "https://gashapon.jp/shop/shop.php?shop_code=S90001416",
      "verifiedAt": "2026-07-13"
    },
    {
      "id": "gashadepa-akeno-acrosstown",
      "brand": "ガシャポンのデパート",
      "name": "ガシャポンのデパートあけのアクロスタウン店",
      "region": "kyushu",
      "pref": "大分県",
      "area": "大分県・大分",
      "address": "大分県大分市明野東1-1-1 あけのアクロスタウン 4F",
      "lat": 33.2240833,
      "lon": 131.652358,
      "sourceUrl": "https://gashapon.jp/shop/shop.php?shop_code=S90000511",
      "verifiedAt": "2026-07-13"
    },
    {
      "id": "gashapon-bandai-tsutaya-nakano",
      "brand": "ガシャポンバンダイオフィシャルショップ",
      "name": "ガシャポンバンダイオフィシャルショップ蔦屋書店 中野店",
      "region": "tokai",
      "pref": "長野県",
      "area": "長野県・中野",
      "address": "長野県中野市大字吉田550",
      "lat": 36.755675170391804,
      "lon": 138.3567823785082,
      "sourceUrl": "https://gashapon.jp/shop/shop.php?shop_code=S90001175",
      "verifiedAt": "2026-07-13"
    },
    {
      "id": "gashapon-bandai-cinemasunshine-yamatokoriyama",
      "brand": "ガシャポンバンダイオフィシャルショップ",
      "name": "ガシャポンバンダイオフィシャルショップシネマサンシャイン大和郡山店",
      "region": "kansai",
      "pref": "奈良県",
      "area": "奈良県・大和郡山",
      "address": "奈良県大和郡山市下三橋町741 イオンモール大和郡山 3F",
      "lat": 34.6512542571435,
      "lon": 135.80218703907187,
      "sourceUrl": "https://gashapon.jp/shop/shop.php?shop_code=S90001756",
      "verifiedAt": "2026-07-13"
    },
    {
      "id": "ggmori-favore-toyama",
      "brand": "ガチャガチャの森",
      "name": "ガチャガチャの森 ファボーレ富山店",
      "region": "tokai",
      "pref": "富山県",
      "area": "富山県・婦中",
      "address": "富山県富山市婦中町下轡田165-1 ファボーレ富山2F",
      "lat": 36.66265773948624,
      "lon": 137.1714723025712,
      "sourceUrl": "https://gashapon.jp/shop/shop.php?shop_code=S90001682",
      "verifiedAt": "2026-07-13"
    },
    {
      "id": "gashapon-bandai-tsutayaway-gardenpark-wakayama",
      "brand": "ガシャポンバンダイオフィシャルショップ",
      "name": "ガシャポンバンダイオフィシャルショップTSUTAYA WAY ガーデンパーク和歌山店",
      "region": "kansai",
      "pref": "和歌山県",
      "area": "和歌山県・和歌山",
      "address": "和歌山県和歌山市松江字向鵜ノ島1469-1",
      "lat": 34.23933162098501,
      "lon": 135.15376362551908,
      "sourceUrl": "https://gashapon.jp/shop/shop.php?shop_code=S90001652",
      "verifiedAt": "2026-07-13"
    },
    {
      "id": "gashapon-bandai-surugaya-matsuyama-okaido",
      "brand": "ガシャポンバンダイオフィシャルショップ",
      "name": "ガシャポンバンダイオフィシャルショップ駿河屋松山大街道店",
      "region": "chugoku",
      "pref": "愛媛県",
      "area": "愛媛県・大街道",
      "address": "愛媛県松山市大街道2丁目5-9 久保豊第1ビル3F",
      "lat": 33.84074633926759,
      "lon": 132.77052667396327,
      "sourceUrl": "https://gashapon.jp/shop/shop.php?shop_code=S90001460",
      "verifiedAt": "2026-07-13"
    },
    {
      "id": "gashapon-bandai-usagiya-tsutaya-yaita",
      "brand": "ガシャポンバンダイオフィシャルショップ",
      "name": "ガシャポンバンダイオフィシャルショップうさぎやTSUTAYA矢板店",
      "region": "kanto",
      "pref": "栃木県",
      "area": "栃木県・矢板",
      "address": "栃木県矢板市末広町20-1 2F",
      "lat": 36.8054072,
      "lon": 139.9346475,
      "sourceUrl": "https://gashapon.jp/shop/shop.php?shop_code=S90000963",
      "verifiedAt": "2026-07-13"
    },
    {
      "id": "gashacoco-aeonmall-yamagata-minami",
      "brand": "gashacoco（ガシャココ）",
      "name": "ガシャココイオンモール山形南",
      "region": "tohoku",
      "pref": "山形県",
      "area": "山形県・山形",
      "address": "山形県山形市若宮3-7-8 イオンモール山形南2F",
      "lat": 38.2266622,
      "lon": 140.3060975,
      "sourceUrl": "https://gashapon.jp/shop/shop.php?shop_code=S90001086",
      "verifiedAt": "2026-07-13"
    },
    {
      "id": "gashadepa-akita-opa",
      "brand": "ガシャポンのデパート",
      "name": "ガシャポンのデパート秋田OPA店",
      "region": "tohoku",
      "pref": "秋田県",
      "area": "秋田県・秋田",
      "address": "秋田県秋田市千秋久保田町4-2 秋田OPA 5F",
      "lat": 39.7178406,
      "lon": 140.128159,
      "sourceUrl": "https://gashapon.jp/shop/shop.php?shop_code=S90000848",
      "verifiedAt": "2026-07-13"
    },
    {
      "id": "gashapon-bandai-cinemasunshine-kahoku",
      "brand": "ガシャポンバンダイオフィシャルショップ",
      "name": "ガシャポンバンダイオフィシャルショップシネマサンシャインかほく店",
      "region": "tokai",
      "pref": "石川県",
      "area": "石川県・かほく",
      "address": "石川県かほく市内日角タ25 イオンモールかほく2F",
      "lat": 36.708886677125896,
      "lon": 136.70137878477934,
      "sourceUrl": "https://gashapon.jp/shop/shop.php?shop_code=S90001647",
      "verifiedAt": "2026-07-13"
    }
  ]
}
