{
  "note": "店舗追加キュー。GitHub Actions（.github/workflows/daily-stores.yml）が毎日 dripPerDay 件ずつ先頭から data/spots.js へ反映し、使った分をここから消し込みます。空になったら自動で何もしません（no-op）。店舗を足すときは queue 配列へ data/spots.js と同じ形のオブジェクトを追記してください。id は重複不可（重複は自動スキップ）。lat/lon は施設のおおよその位置。出典：ガシャポン公式（gashapon.jp）／バンダイナムコアミューズメント公式（bandainamco-am.co.jp）。",
  "dripPerDay": 2,
  "queue": [
    {
      "id": "gashadepa-iy-abeno",
      "brand": "ガシャポンのデパート",
      "name": "ガシャポンのデパート イトーヨーカドー あべの店",
      "region": "kansai",
      "pref": "大阪府",
      "area": "大阪府・天王寺",
      "address": "大阪府大阪市阿倍野区阿倍野筋1-6-1 イトーヨーカドー あべの店 2F",
      "machines": 640,
      "lat": 34.6448,
      "lon": 135.5136,
      "access": "イトーヨーカドー あべの店 2F（天王寺駅から徒歩約2分）"
    },
    {
      "id": "gashacoco-lalaport-expocity",
      "brand": "gashacoco（ガシャココ）",
      "name": "gashacoco ららぽーとEXPOCITY店",
      "region": "kansai",
      "pref": "大阪府",
      "area": "大阪府・万博記念公園",
      "address": "大阪府吹田市千里万博公園2-1 ららぽーとEXPOCITY 3F",
      "tel": "080-4477-4243",
      "hours": "10:00〜21:00",
      "lat": 34.8058,
      "lon": 135.5341,
      "access": "ららぽーとEXPOCITY 3F（大阪モノレール万博記念公園駅から徒歩約2分）"
    }
  ]
}
